{
  "_class": "text",
  "attributedString": {
    "_class": "attributedString",
    "attributes": [
      {
        "_class": "stringAttribute",
        "attributes": {
          "MSAttributedStringColorAttribute": {
            "_class": "color",
            "alpha": 1,
            "blue": 0,
            "green": 0,
            "red": 0
          },
          "MSAttributedStringFontAttribute": {
            "_class": "fontDescriptor",
            "attributes": {
              "name": "WorkSans-Medium",
              "size": 24
            }
          },
          "kerning": -0.5,
          "paragraphStyle": {
            "_class": "paragraphStyle",
            "alignment": 0,
            "allowsDefaultTighteningForTruncation": 0,
            "baseWritingDirection": 0,
            "headerLevel": 1,
            "maximumLineHeight": 24,
            "minimumLineHeight": 24,
            "paragraphSpacing": 10
          },
          "textStyleVerticalAlignmentKey": 0
        },
        "length": 70,
        "location": 0
      },
      {
        "_class": "stringAttribute",
        "attributes": {
          "MSAttributedStringColorAttribute": {
            "_class": "color",
            "alpha": 1,
            "blue": 0,
            "green": 0,
            "red": 0
          },
          "MSAttributedStringFontAttribute": {
            "_class": "fontDescriptor",
            "attributes": {
              "name": "WorkSans-Medium",
              "size": 24
            }
          },
          "kerning": 0,
          "paragraphStyle": {
            "_class": "paragraphStyle",
            "alignment": 0,
            "allowsDefaultTighteningForTruncation": 0,
            "baseWritingDirection": 0,
            "headerLevel": 1,
            "maximumLineHeight": 24,
            "minimumLineHeight": 24,
            "paragraphSpacing": 10
          },
          "textStyleVerticalAlignmentKey": 0
        },
        "length": 1,
        "location": 70
      }
    ],
    "string": "Dancing with the Stars Just Handed Out the Season’s First Perfect Score"
  },
  "automaticallyDrawOnUnderlyingPath": false,
  "booleanOperation": -1,
  "do_objectID": "C8195901-9E00-405C-BE61-F3EB317B08EE",
  "dontSynchroniseWithSymbol": false,
  "exportOptions": {
    "_class": "exportOptions",
    "do_objectID": "E45234BD-DEEC-4727-B56E-A9AC9AB522A5",
    "exportFormats": [
    ],
    "includedLayerIds": [
    ],
    "layerOptions": 0,
    "shouldTrim": false
  },
  "frame": {
    "_class": "rect",
    "constrainProportions": false,
    "do_objectID": "F8DE46C7-0917-4E24-8593-954809212251",
    "height": 48,
    "width": 459,
    "x": 835,
    "y": 1597
  },
  "glyphBounds": "{{0, 2}, {459, 43}}",
  "isFixedToViewport": false,
  "isFlippedHorizontal": false,
  "isFlippedVertical": false,
  "isLocked": false,
  "isVisible": true,
  "layerListExpandedType": 0,
  "lineSpacingBehaviour": 2,
  "name": "Dancing with the Sta",
  "nameIsFixed": false,
  "resizingConstraint": 47,
  "resizingType": 0,
  "rotation": 0,
  "shouldBreakMaskChain": false,
  "style": {
    "_class": "style",
    "do_objectID": "CD614FC2-5AB1-4623-9D9F-2AAA864B4F4F",
    "endMarkerType": 0,
    "miterLimit": 10,
    "startMarkerType": 0,
    "textStyle": {
      "_class": "textStyle",
      "do_objectID": "255A1890-CA6E-4D4A-BEC0-D8D7A85A0049",
      "encodedAttributes": {
        "MSAttributedStringColorAttribute": {
          "_class": "color",
          "alpha": 1,
          "blue": 0,
          "green": 0,
          "red": 0
        },
        "MSAttributedStringFontAttribute": {
          "_class": "fontDescriptor",
          "attributes": {
            "name": "WorkSans-Medium",
            "size": 24
          }
        },
        "kerning": -0.5,
        "paragraphStyle": {
          "_class": "paragraphStyle",
          "alignment": 0,
          "allowsDefaultTighteningForTruncation": 0,
          "baseWritingDirection": 0,
          "headerLevel": 1,
          "maximumLineHeight": 24,
          "minimumLineHeight": 24,
          "paragraphSpacing": 10
        },
        "textStyleVerticalAlignmentKey": 0
      },
      "verticalAlignment": 0
    },
    "windingRule": 1
  },
  "textBehaviour": 0
}